flake8_block_comment.py
flake8_block_comment-0.0.3.dist-info/LICENSE
flake8_block_comment-0.0.3.dist-info/METADATA
flake8_block_comment-0.0.3.dist-info/WHEEL
flake8_block_comment-0.0.3.dist-info/entry_points.txt
flake8_block_comment-0.0.3.dist-info/top_level.txt
flake8_block_comment-0.0.3.dist-info/RECORD
