Metadata-Version: 2.1
Name: flake8-block-comment
Version: 0.0.3
Summary: Block comment checker
Home-page: https://github.com/ikemo3/flake8-block-comment
Author: Hideki Ikemoto
Author-email: ikemo333@gmail.com
License: MIT
Platform: UNKNOWN
Classifier: Framework :: Flake8
Classifier: Environment :: Console
Classifier: Intended Audience :: Developers
Classifier: License :: OSI Approved :: MIT License
Classifier: Programming Language :: Python
Classifier: Programming Language :: Python :: 3
Classifier: Topic :: Software Development :: Libraries :: Python Modules
Classifier: Topic :: Software Development :: Quality Assurance
Requires-Dist: pycodestyle (<3.0.0,>=2.0.0)
